egpt/__init__.py
egpt/_modidx.py
egpt/core.py
egpt-0.0.1.dist-info/LICENSE
egpt-0.0.1.dist-info/METADATA
egpt-0.0.1.dist-info/WHEEL
egpt-0.0.1.dist-info/entry_points.txt
egpt-0.0.1.dist-info/top_level.txt
egpt-0.0.1.dist-info/RECORD
